{
  "id": "audioseg",
  "name": "AudioSegmenter",
  "descr": "AudioSegmenter is a tool to segment audio files into several tracks. Bounds of the tracks are indicated in an annotated file of any format supported by SPPAS (xra, TextGrid, eaf, ...).",
  "icon": "audioseg.png",
  "version": "2.1",

  "commands": {
    "windows": "python.exe PLUGIN_PATH/audioseg.py",
    "macos": "python PLUGIN_PATH/audioseg.py",
    "linux": "python PLUGIN_PATH/audioseg.py"
  },

  "options": [

    {
      "id": "-i",
      "type": "file",
      "value": "input"
    },

    {
      "id": "-t",
      "type": "string",
      "value": "IPUs",
      "text": "Name of the tier indicating the tracks:"
    },

    {
      "id": "-e",
      "type": "string",
      "value": ".xra",
      "text": "File extension for the tracks (beginning with a dot):"
    }

  ]

}